nonebot_plugin_wordcloud/SourceHanSans.otf
nonebot_plugin_wordcloud/__init__.py
nonebot_plugin_wordcloud/compat.py
nonebot_plugin_wordcloud/config.py
nonebot_plugin_wordcloud/data_source.py
nonebot_plugin_wordcloud/model.py
nonebot_plugin_wordcloud/schedule.py
nonebot_plugin_wordcloud/utils.py
nonebot_plugin_wordcloud/migrations/557fef3a156f_init_db.py
nonebot_plugin_wordcloud/migrations/__init__.py
nonebot_plugin_wordcloud/migrations/ade8cdca5470_migrate_datastore_data.py
nonebot_plugin_wordcloud-0.9.0.dist-info/METADATA
nonebot_plugin_wordcloud-0.9.0.dist-info/WHEEL
nonebot_plugin_wordcloud-0.9.0.dist-info/licenses/LICENSE
nonebot_plugin_wordcloud-0.9.0.dist-info/RECORD
