Metadata-Version: 2.4
Name: nonebot-plugin-wordcloud
Version: 0.9.0
Summary: 适用于 NoneBot2 的词云插件
Project-URL: Homepage, https://github.com/he0119/nonebot-plugin-wordcloud
Project-URL: Repository, https://github.com/he0119/nonebot-plugin-wordcloud.git
Project-URL: Issues, https://github.com/he0119/nonebot-plugin-wordcloud/issues
Project-URL: Changelog, https://github.com/he0119/nonebot-plugin-wordcloud/blob/main/CHANGELOG.md
Author-email: uy_sun <hmy0119@gmail.com>
License: MIT License
License-File: LICENSE
Requires-Python: >=3.9
Requires-Dist: emoji>=1.6.3
Requires-Dist: jieba>=0.42.1
Requires-Dist: nonebot-plugin-alconna>=0.49.0
Requires-Dist: nonebot-plugin-apscheduler>=0.4.0
Requires-Dist: nonebot-plugin-cesaa<0.6.0,>=0.5.0
Requires-Dist: nonebot-plugin-localstore>=0.6.0
Requires-Dist: nonebot-plugin-orm>=0.7.0
Requires-Dist: nonebot-plugin-uninfo>=0.6.2
Requires-Dist: nonebot2[fastapi]>=2.2.0
Requires-Dist: tzdata
Requires-Dist: wordcloud>=1.8.1
Provides-Extra: datastore
Requires-Dist: nonebot-plugin-datastore>=1.2.0; extra == 'datastore'
